SynapseAI/__init__.py
SynapseAI/config.py
SynapseAI/main.py
SynapseAI/pdf_processor.py
SynapseAI/utils.py
SynapseAI/web_crawler.py
enginex/__init__.py
enginex/config.py
enginex/main.py
enginex/pdf_processor.py
enginex/utils.py
enginex/web_crawler.py
engineX-0.5.6.dist-info/METADATA
engineX-0.5.6.dist-info/WHEEL
engineX-0.5.6.dist-info/entry_points.txt
engineX-0.5.6.dist-info/top_level.txt
engineX-0.5.6.dist-info/RECORD
