Metadata-Version: 2.1
Name: engineX
Version: 0.5.6
Requires-Dist: requests
Requires-Dist: beautifulsoup4
Requires-Dist: pandas
Requires-Dist: docx2txt
Requires-Dist: langchain
Requires-Dist: langchain-community
Requires-Dist: langchain-text-splitters
Requires-Dist: faiss-cpu
Requires-Dist: numpy
Requires-Dist: Pillow
Requires-Dist: pytesseract
Requires-Dist: PyPDF2
